32-bit multiplier/Multiplier.v
module multiplier (in1,in2,final);

// initalize i/o port
input [31:0] in1,in2;
output [31:0]final;

// interim wire
wire [22:0]M1,M2;
wire [7:0]E1,E2;
wire s1,s2;
wire[8:0] eigth_bit_adder,nine_bit_sub;
wire [47:0] multi;

// Design of the circuit

assign M1 =  in1[22:0];
assign M2 =  in2[22:0];
assign E1 =  in1[30:23];
assign E2 =  in2[30:23];    

assign eigth_bit_adder = E1 + E2;
assign nine_bit_sub = eigth_bit_adder - 9'b001111111;

assign  final[30:23] = nine_bit_sub;

assign multi = M1*M2;

assign final[22:0] = multi;

assign s1 = in1[31];
assign s2 = in2[31];

assign final [31] = s1^s2;

endmodule

32-bit multiplier/Multiplier_tb.v
// `include "Multiplier.v"

module multiplier_tb ;
reg [31:0] in1,in2;
wire [31:0]final;

    multiplier dut (.in1(in1),.in2(in2),.final(final));

initial begin

      // Test cases
    // Input values are in IEEE 754 format
    in1 = 32'h3F800000; // 1.0
    in2 = 32'h40000000; // 2.0
    #10  // Expected 2.0

    in1 = 32'hC0000000; // -2.0
    in2 = 32'h40000000; // 2.0
    #10  // Expected -4.0

    in1 = 32'h40400000; // 3.0
    in2 = 32'h40400000; // 3.0
    #10  // Expected 9.0

    in1 = 32'h3F800000; // 1.0
    in2 = 32'h00000000; // 0.0
    #10  // Expected 0.0

    in1 = 32'h7F800000; // Infinity
    in2 = 32'h3F800000; // 1.0
    #10  // Expected Infinity

    in1 = 32'h7F800000; // Infinity
    in2 = 32'h7F800000; // Infinity
    #10  // Expected Infinity

    in1 = 32'h7F800000; // Infinity
    in2 = 32'hFF800000; // -Infinity
    #10  // Expected -Infinity

    in1 = 32'hFFFFFFFF; // NaN
    in2 = 32'h3F800000; // 1.0
    #10  // Expected NaN

    // End simulation
     $finish;
end
 initial begin
        $dumpfile("top_dump.vcd");
        $dumpvars(0);
    end

endmodule

32-bit multiplier/top_dump.vcd
$date
	Sat Jan 18 22:52:58 2025
$end
$version
	Icarus Verilog
$end
$timescale
	1s
$end
$scope module multiplier_tb $end
$var wire 32 ! final [31:0] $end
$var reg 32 " in1 [31:0] $end
$var reg 32 # in2 [31:0] $end
$scope module dut $end
$var wire 32 $ in1 [31:0] $end
$var wire 32 % in2 [31:0] $end
$var wire 1 & s2 $end
$var wire 1 ' s1 $end
$var wire 9 ( nine_bit_sub [8:0] $end
$var wire 48 ) multi [47:0] $end
$var wire 32 * final [31:0] $end
$var wire 9 + eigth_bit_adder [8:0] $end
$var wire 23 , M2 [22:0] $end
$var wire 23 - M1 [22:0] $end
$var wire 8 . E2 [7:0] $end
$var wire 8 / E1 [7:0] $end
$upscope $end
$upscope $end
$enddefinitions $end
$comment Show the parameter values. $end
$dumpall
$end
#0
$dumpvars
b1111111 /
b10000000 .
b0 -
b0 ,
b11111111 +
b1000000000000000000000000000000 *
b0 )
b10000000 (
0'
0&
b1000000000000000000000000000000 %
b111111100000000000000000000000 $
b1000000000000000000000000000000 #
b111111100000000000000000000000 "
b1000000000000000000000000000000 !
$end
#10
b11000000100000000000000000000000 !
b11000000100000000000000000000000 *
b10000001 (
b100000000 +
b10000000 /
1'
b11000000000000000000000000000000 "
b11000000000000000000000000000000 $
#20
b1000000100000000000000000000000 !
b1000000100000000000000000000000 *
b100000000000000000000000000000000000000000000 )
b10000000000000000000000 ,
b10000000000000000000000 -
0'
b1000000010000000000000000000000 #
b1000000010000000000000000000000 %
b1000000010000000000000000000000 "
b1000000010000000000000000000000 $
#30
b0 !
b0 *
b0 ,
b0 .
b0 )
b0 -
b0 (
b1111111 +
b1111111 /
b0 #
b0 %
b111111100000000000000000000000 "
b111111100000000000000000000000 $
#40
b1111111100000000000000000000000 !
b1111111100000000000000000000000 *
b1111111 .
b11111111 (
b101111110 +
b11111111 /
b111111100000000000000000000000 #
b111111100000000000000000000000 %
b1111111100000000000000000000000 "
b1111111100000000000000000000000 $
#50
b111111100000000000000000000000 !
b111111100000000000000000000000 *
b101111111 (
b111111110 +
b11111111 .
b1111111100000000000000000000000 #
b1111111100000000000000000000000 %
#60
b10111111100000000000000000000000 !
b10111111100000000000000000000000 *
1&
b11111111100000000000000000000000 #
b11111111100000000000000000000000 %
#70
b11111111100000000000000000000000 !
b11111111100000000000000000000000 *
b11111111 (
b101111110 +
b1111111 .
0&
b11111111111111111111111 -
1'
b111111100000000000000000000000 #
b111111100000000000000000000000 %
b11111111111111111111111111111111 "
b11111111111111111111111111111111 $
