16-bit Adder Subtractor/normalisation.v



// module normalization (
//     input [13:0] mantisa,       // Input mantisa (including intrinsic bit)
//     input [4:0] exp,            // Input exponent
//     output reg [10:0] mantisa_out, // Output normalized mantisa (11 bits)
//     output reg [4:0] exp_out,   // Output normalized exponent
//     output reg overflow_flag,   // Overflow flag
//     output sign_res             // Sign of the result
// );

//     // Sign extraction and absolute value for mantisa
//     wire signed_bit = mantisa[13]; // Extract the sign bit
//     wire [12:0] abs_mantisa = (signed_bit ? -mantisa[12:0] : mantisa[12:0]);
//     reg [12:0] normalized_mantisa;
//     reg [4:0] temp_exp;
    
//     assign sign_res = signed_bit; // Pass the sign as output

//     always @(*) begin
//         // Initialize outputs
//         mantisa_out = 11'b0;
//         exp_out = 5'b0;
//         overflow_flag = 0;

//         if (abs_mantisa == 13'b0) begin
//             // Case when mantisa is zero
//             mantisa_out = 11'b0;
//             exp_out = 5'b0;
//         end else begin
//             // Normalize the mantisa
//              normalized_mantisa = abs_mantisa;
//              temp_exp = exp;

//             // Shift mantisa left until MSB is 1 or exponent reaches zero
//             while (normalized_mantisa[12] == 0 && temp_exp > 0) begin
//                 normalized_mantisa = normalized_mantisa << 1;
//                 temp_exp = temp_exp - 1;
//             end

//             // Shift mantisa right if necessary to fit into 11 bits
//             while (normalized_mantisa[12:11] > 2'b01 && temp_exp < 5'b11111) begin
//                 normalized_mantisa = normalized_mantisa >> 1;
//                 temp_exp = temp_exp + 1;
//             end

//             // Assign normalized outputs
//             mantisa_out = normalized_mantisa[12:2]; // Keep 11 bits
//             exp_out = temp_exp;

//             // Handle overflow
//             if (temp_exp == 5'b11111) begin
//                 overflow_flag = 1; // Set overflow flag if exponent maxes out
//                 mantisa_out = 11'b0;
//             end 
//         end
//     end
// endmodule

module normalization (
    input [13:0] mantisa,
    input [4:0] exp,
    output reg [10:0] mantisa_out,
    output reg [4:0] exp_out,
    output reg overflow_flag,
    output reg sign_res
);

 reg [12:0] normalized_mantissa;
  reg [4:0] temp_exp ;

    wire sign_bit = mantisa[13];
    wire [12:0] abs_mantissa = sign_bit ? -mantisa[12:0] : mantisa[12:0];

    always @(*) begin
        // Default initializations
        mantisa_out = 11'd0;
        exp_out = 5'd0;
        overflow_flag = 1'b0;
        sign_res = sign_bit;

        if (abs_mantissa == 13'd0) begin
            // Zero case - clear everything
            mantisa_out = 11'd0;
            exp_out = 5'd0;
        end else begin
            // Normalization logic
             normalized_mantissa = abs_mantissa;
             temp_exp = exp;

            // Left shift until MSB is 1
            while (normalized_mantissa[12] == 1'b0 && temp_exp > 5'd0) begin
                normalized_mantissa = normalized_mantissa << 1;
                temp_exp = temp_exp - 1'b1;
            end

            // Right shift if needed to prevent overflow
            while (normalized_mantissa[12:11] > 2'b01 && temp_exp < 5'b11111) begin
                normalized_mantissa = normalized_mantissa >> 1;
                temp_exp = temp_exp + 1'b1;
            end

            // Final output assignment
            mantisa_out = normalized_mantissa[12:2];
            exp_out = temp_exp;

            // Overflow check
            if (temp_exp == 5'b11111) begin
                overflow_flag = 1'b1;
                mantisa_out = 11'd0;
                exp_out = 5'b11111;
            end  
            
             if (temp_exp== 5'b11111 || normalized_mantissa[11:2]== 10'b1111111111) begin
               
                overflow_flag <= 1'b1;
            end
        end
    end
endmodule

16-bit Adder Subtractor/addition_s.v


module addition_s (
   mantisa1,mantisa2,sign1,sign2,mantisa_out
);

    input [12:0] mantisa1,mantisa2;
    input sign1,sign2;
    output  [13:0] mantisa_out;
    

    wire [12:0] Mantisa_w1,Mantisa_w2 ;
   assign Mantisa_w1 = sign1 ? (-mantisa1): mantisa1;
   assign Mantisa_w2 = sign2 ? (-mantisa2): mantisa2;



    assign mantisa_out = Mantisa_w1 + Mantisa_w2;

    

endmodule

16-bit Adder Subtractor/compare_and_shift.v
module compare_and_shift (
    input [12:0] mantisa1,           // 10-bit mantissa of input 1
    input [12:0] mantisa2,           // 10-bit mantissa of input 2
    input [4:0] exp1,               // 5-bit exponent of input 1
    input [4:0] exp2,               // 5-bit exponent of input 2
    output reg [12:0] mantisa1_new, // 11-bit aligned mantissa of input 1
    output reg [12:0] mantisa2_new, // 11-bit aligned mantissa of input 2
    output reg [4:0] new_exp        // 5-bit aligned exponent
);

    wire [4:0] exp_dif;              // Exponent difference
    

    // Calculate exponent difference
    assign exp_dif = (exp1 > exp2) ? (exp1 - exp2) : (exp2 - exp1);

    always @(*) begin
        // Initialize outputs to avoid latches
        mantisa1_new = 0;
        mantisa2_new = 0;
        new_exp = 0;

       
        // Align mantissas based on exponent difference
        if (exp1 > exp2) begin
            mantisa1_new = mantisa1;              // Keep mantisa1 as is
            mantisa2_new = mantisa2 >> exp_dif;   // Right-shift mantisa2
            new_exp = exp1+8'd1;                        // Use the larger exponent
        end else if (exp1 < exp2) begin
            mantisa1_new = mantisa1 >> exp_dif;   // Right-shift mantisa1
            mantisa2_new = mantisa2;              // Keep mantisa2 as is
            new_exp = exp2+8'd1;                        // Use the larger exponent
        end else begin
            mantisa1_new = mantisa1;              // Exponents are the same
            mantisa2_new = mantisa2;              // No need to shift
            new_exp = exp1+8'd1;                        // Exponents are equal
        end
    end

endmodule

16-bit Adder Subtractor/adder_single_cycle.v
// `include "addition_s.v"
// `include "compare_and_shift.v"
// `include "normalisation.v"


// module adder_single_cycle (
//     input clk,                 // Clock signal
//     input rst,                 // Reset signal
//     input i_valid,             // Input valid signal
//     input [15:0] i_a,          // IEEE 754 input A
//     input [15:0] i_b,          // IEEE 754 input B
//     output reg [15:0] o_res,   // IEEE 754 normalized result
//     output  Overflow,       // Overflow flag
//     output reg o_res_vld       // Output result valid signal
// );

//     // Internal wires
//    wire [12:0] mantisa1_w,mantisa2_w;
//    wire [4:0] exp1_w,exp2_w;
//    wire [12:0] mantisa1_new_w,mantisa2_new_w;
//    wire [4:0]new_exp_w,exp_out_w; 
//    wire [13:0] mantisa_out_w;
//    wire sign_out_w,overflow_flag_w;
//    wire [10:0] mantisa_out;
//    wire  zero_a,zero_b,exception_a,exception_b,zero_ip;
//    wire  [15:0] res;

// always @(posedge clk)
// begin
// 	if(rst)
// 	begin
// 		o_res <= 16'd0;
// 		o_res_vld <= 1'b0;
        
// 	end
	
// 	else 
// 	begin
// 		o_res <= res;
// 		o_res_vld <= i_valid;
        
// 	end
	
// end


// assign exception_a=(&i_a[14:10]);
// assign exception_b=(&i_b[14:10]);
// assign zero_a=!(|i_a[14:0]);
// assign zero_b=!(|i_b[14:0]);
// assign zero_ip= zero_a && zero_b;



// assign mantisa1_w = (|i_a[14:10]) ? {3'b001,i_a[9:0]} : {3'b000,i_a[9:0]};   // assigned 13 bits		  
// assign mantisa2_w = (|i_b[14:10]) ? {3'b001,i_b[9:0]} : {3'b000,i_b[9:0]};


  

//     // Submodule instances
//     compare_and_shift u_compare_and_shift (
//         .mantisa1(mantisa1_w),
//         .mantisa2(mantisa2_w),
//         .exp1(i_a[14:10]),
//         .exp2(i_b[14:10]),
//         .mantisa1_new(mantisa1_new_w),
//         .mantisa2_new(mantisa2_new_w),
//         .new_exp(new_exp_w)
//     );

//     addition_s u_addition_s (
//          .mantisa1(mantisa1_new_w),
//          .mantisa2(mantisa2_new_w),
//          .sign1(i_a[15]),
//          .sign2(i_b[15]),
//          .mantisa_out(mantisa_out_w)
        
//     );

//     normalization u_normalisation (
//          .mantisa(mantisa_out_w),
//          .exp(new_exp_w),
//          .mantisa_out(mantisa_out),
//          .exp_out(exp_out_w),
//          .overflow_flag(Overflow),
//         .sign_res(sign_out_w)
//     );

//   assign res=(zero_ip?({sign_out_w,15'd0}):exception_a?{i_a[15],5'b11111,10'b0}:exception_b?{i_b[15],5'b11111,10'b0}:Overflow?{1'b0,5'b11111,10'b0}:zero_a?i_b:zero_b?i_a:{sign_out_w,exp_out_w,mantisa_out[9:0]});


// endmodule


`include "addition_s.v"
`include "compare_and_shift.v"
`include "normalisation.v"

module adder_single_cycle (
    input clk,                  // Clock signal
    input rst,                  // Reset signal
    input i_valid,              // Input valid signal
    input [15:0] i_a,           // IEEE 754 input A
    input [15:0] i_b,           // IEEE 754 input B
    output reg [15:0] o_res,    // IEEE 754 normalized result
    output reg Overflow,        // Overflow flag
    output reg o_res_vld        // Output result valid signal
);

    // Internal wires
    wire [12:0] mantisa1_w, mantisa2_w;
    wire [4:0] exp1_w, exp2_w;
    wire [12:0] mantisa1_new_w, mantisa2_new_w;
    wire [4:0] new_exp_w, exp_out_w; 
    wire [13:0] mantisa_out_w;
    wire sign_out_w, overflow_flag_w;
    wire [10:0] mantisa_out;
    wire zero_a, zero_b, exception_a, exception_b, zero_ip;
    wire [15:0] res;

    // Registers for synchronized outputs
    always @(posedge clk or posedge rst) begin
        if (rst) begin
            o_res <= 16'd0;
            o_res_vld <= 1'b0;
            Overflow <= 1'b0;
        end else begin
            o_res <= res;
            o_res_vld <= i_valid;
            Overflow <= overflow_flag_w;
        end
    end

    // Exception and zero handling
    assign exception_a = (&i_a[14:10]);
    assign exception_b = (&i_b[14:10]);
    assign zero_a = !(|i_a[14:0]);
    assign zero_b = !(|i_b[14:0]);
    assign zero_ip = zero_a && zero_b;

    // Mantissa extraction
    assign mantisa1_w = (|i_a[14:10]) ? {3'b001, i_a[9:0]} : {3'b000, i_a[9:0]};   // Assigned 13 bits		  
    assign mantisa2_w = (|i_b[14:10]) ? {3'b001, i_b[9:0]} : {3'b000, i_b[9:0]};

    // Submodule instances
    compare_and_shift u_compare_and_shift (
        .mantisa1(mantisa1_w),
        .mantisa2(mantisa2_w),
        .exp1(i_a[14:10]),
        .exp2(i_b[14:10]),
        .mantisa1_new(mantisa1_new_w),
        .mantisa2_new(mantisa2_new_w),
        .new_exp(new_exp_w)
    );

    addition_s u_addition_s (
        .mantisa1(mantisa1_new_w),
        .mantisa2(mantisa2_new_w),
        .sign1(i_a[15]),
        .sign2(i_b[15]),
        .mantisa_out(mantisa_out_w)
    );

    normalization u_normalisation (
        .mantisa(mantisa_out_w),
        .exp(new_exp_w),
        .mantisa_out(mantisa_out),
        .exp_out(exp_out_w),
        .overflow_flag(overflow_flag_w),
        .sign_res(sign_out_w)
    );

    // Output result assignment
    assign res = (overflow_flag_w) ? {1'b0, 5'b11111, 10'b0} : // Handle overflow as infinity
                 (zero_ip) ? {sign_out_w, 15'd0} :       // Both inputs are zero
                 (exception_a) ? {i_a[15], 5'b11111, 10'b0} : // Handle exception in A
                 (exception_b) ? {i_b[15], 5'b11111, 10'b0} : // Handle exception in B
                 (zero_a) ? i_b :                       // A is zero
                 (zero_b) ? i_a :                       // B is zero
                 {sign_out_w, exp_out_w, mantisa_out[9:0]}; // Normalized result

endmodule

16-bit Adder Subtractor/tb_adder_single_cycle.v
`timescale 1ns/1ps

module tb_adder_single_cycle;

    // Inputs
    reg clk;
    reg rst;
    reg i_valid;
    reg [15:0] i_a;
    reg [15:0] i_b;

    // Outputs
    wire [15:0] o_res;
    wire Overflow;
    wire o_res_vld;

    // Instantiate the Unit Under Test (UUT)
    adder_single_cycle uut (
        .clk(clk),
        .rst(rst),
        .i_valid(i_valid),
        .i_a(i_a),
        .i_b(i_b),
        .o_res(o_res),
        .Overflow(Overflow),
        .o_res_vld(o_res_vld)
    );

    // Clock generation
    initial begin
        clk = 0;
        forever #5 clk = ~clk; // 10ns clock period
    end

    // Test cases
    initial begin
        // Monitor signals
        $monitor("Time: %0d | i_a: %b | i_b: %b | o_res: %b | Overflow: %b | o_res_vld: %b", 
                 $time, i_a, i_b, o_res, Overflow, o_res_vld);

        // Initialize dumpfile for waveform
        $dumpfile("adder_single_cycle.vcd");
        $dumpvars(0, tb_adder_single_cycle);

        // Initialize inputs
        rst = 1;
        i_valid = 0;
        i_a = 0;
        i_b = 0;

        // Reset the system
        #10 rst = 0;

        // Test Case 1: Add two normalized positive numbers
        #10;
        i_valid = 1;
        i_a = 16'b0100010100000000; // +5.0
        i_b = 16'b0100001000000000; // +2.5
        // Expected output: o_res = 0110011000000000 (+7.5), Overflow = 0
        #10 i_valid = 0;

        // Test Case 2: Add a positive and a negative number
        #20;
        i_valid = 1;
        i_a = 16'b0100010100000000; // +5.0
        i_b = 16'b1100001000000000; // -2.5
        // Expected output: o_res = 0100001000000000 (+2.5), Overflow = 0
        #10 i_valid = 0;

        // Test Case 3: Add two negative numbers
        #20;
        i_valid = 1;
        i_a = 16'b1100010100000000; // -5.0
        i_b = 16'b1100001000000000; // -2.5
        // Expected output: o_res = 1110011000000000 (-7.5), Overflow = 0
        #10 i_valid = 0;

        // Test Case 4: Add numbers with different exponents
        #20;
        i_valid = 1;
        i_a = 16'b0100010100000000; // +5.0
        i_b = 16'b0100110000000000; // +48.0
        // Expected output: o_res = 0100110010100000 (+53.0), Overflow = 0
        #10 i_valid = 0;

        // Test Case 5: Overflow occurs
        #20;
        i_valid = 1;
        i_a = 16'b0111101111111111; // Maximum positive value (~65504.0)
        i_b = 16'b0100110000000000; // +48.0
        // Expected output: o_res = Undefined, Overflow = 1
        #10 i_valid = 0;

        // Test Case 6: Add zero to a number
        #20;
        i_valid = 1;
        i_a = 16'b0100010100000000; // +5.0
        i_b = 16'b0000000000000000; // 0.0
        // Expected output: o_res = 0100010100000000 (+5.0), Overflow = 0
        #10 i_valid = 0;

        // Test Case 7: Both inputs are zero
        #20;
        i_valid = 1;
        i_a = 16'b0000000000000000; // 0.0
        i_b = 16'b0000000000000000; // 0.0
        // Expected output: o_res = 0000000000000000 (0.0), Overflow = 0
        #10 i_valid = 0;

        // End simulation
        #50;
        $finish;
    end

endmodule

16-bit Adder Subtractor/adder_single_cycle.vcd
$date
	Sat Jan 25 22:23:30 2025
$end
$version
	Icarus Verilog
$end
$timescale
	1ps
$end
$scope module tb_adder_single_cycle $end
$var wire 1 ! o_res_vld $end
$var wire 16 " o_res [15:0] $end
$var wire 1 # Overflow $end
$var reg 1 $ clk $end
$var reg 16 % i_a [15:0] $end
$var reg 16 & i_b [15:0] $end
$var reg 1 ' i_valid $end
$var reg 1 ( rst $end
$scope module uut $end
$var wire 1 $ clk $end
$var wire 16 ) i_a [15:0] $end
$var wire 16 * i_b [15:0] $end
$var wire 1 ' i_valid $end
$var wire 1 ( rst $end
$var wire 1 + zero_ip $end
$var wire 1 , zero_b $end
$var wire 1 - zero_a $end
$var wire 1 . sign_out_w $end
$var wire 16 / res [15:0] $end
$var wire 1 0 overflow_flag_w $end
$var wire 5 1 new_exp_w [4:0] $end
$var wire 14 2 mantisa_out_w [13:0] $end
$var wire 11 3 mantisa_out [10:0] $end
$var wire 13 4 mantisa2_w [12:0] $end
$var wire 13 5 mantisa2_new_w [12:0] $end
$var wire 13 6 mantisa1_w [12:0] $end
$var wire 13 7 mantisa1_new_w [12:0] $end
$var wire 5 8 exp_out_w [4:0] $end
$var wire 1 9 exception_b $end
$var wire 1 : exception_a $end
$var reg 1 # Overflow $end
$var reg 16 ; o_res [15:0] $end
$var reg 1 ! o_res_vld $end
$scope module u_addition_s $end
$var wire 1 < sign1 $end
$var wire 1 = sign2 $end
$var wire 14 > mantisa_out [13:0] $end
$var wire 13 ? mantisa2 [12:0] $end
$var wire 13 @ mantisa1 [12:0] $end
$var wire 13 A Mantisa_w2 [12:0] $end
$var wire 13 B Mantisa_w1 [12:0] $end
$upscope $end
$scope module u_compare_and_shift $end
$var wire 5 C exp1 [4:0] $end
$var wire 5 D exp2 [4:0] $end
$var wire 13 E mantisa1 [12:0] $end
$var wire 13 F mantisa2 [12:0] $end
$var wire 5 G exp_dif [4:0] $end
$var reg 13 H mantisa1_new [12:0] $end
$var reg 13 I mantisa2_new [12:0] $end
$var reg 5 J new_exp [4:0] $end
$upscope $end
$scope module u_normalisation $end
$var wire 5 K exp [4:0] $end
$var wire 14 L mantisa [13:0] $end
$var wire 1 M sign_bit $end
$var wire 13 N abs_mantissa [12:0] $end
$var reg 5 O exp_out [4:0] $end
$var reg 11 P mantisa_out [10:0] $end
$var reg 13 Q normalized_mantissa [12:0] $end
$var reg 1 0 overflow_flag $end
$var reg 1 . sign_res $end
$var reg 5 R temp_exp [4:0] $end
$upscope $end
$upscope $end
$upscope $end
$enddefinitions $end
$comment Show the parameter values. $end
$dumpall
$end
#0
$dumpvars
b1 R
bx Q
b0 P
b0 O
b0 N
0M
b0 L
b1 K
b1 J
b0 I
b0 H
b0 G
b0 F
b0 E
b0 D
b0 C
b0 B
b0 A
b0 @
b0 ?
b0 >
0=
0<
b0 ;
0:
09
b0 8
b0 7
b0 6
b0 5
b0 4
b0 3
b0 2
b1 1
00
b0 /
0.
1-
1,
1+
b0 *
b0 )
1(
0'
b0 &
b0 %
0$
0#
b0 "
0!
$end
#5000
1$
#10000
0$
0(
#15000
1$
#20000
b10010 8
b10010 O
b1000000000 3
b1000000000 P
b10010 R
b100000000000 Q
b100000000000 N
b100101000000000 /
b1100000000 A
b100000000000 2
b100000000000 >
b100000000000 L
b10100000000 B
b1100000000 5
b1100000000 ?
b1100000000 I
b10100000000 7
b10100000000 @
b10100000000 H
b11000000000 4
b11000000000 F
0+
b10100000000 6
b10100000000 E
b10010 1
b10010 J
b10010 K
b1 G
0,
b10000 D
0-
b10001 C
0$
b100001000000000 &
b100001000000000 *
b100010100000000 %
b100010100000000 )
1'
#25000
1!
b100101000000000 "
b100101000000000 ;
1$
#30000
0$
0'
#35000
0!
1$
#40000
0$
#45000
1$
#50000
b1100111111000000 /
b10011 R
b111100000000 Q
1.
b10011 8
b10011 O
b1111000000 3
b1111000000 P
b1111000000000 N
1M
b10001000000000 2
b10001000000000 >
b10001000000000 L
b1110100000000 A
1=
0$
b1100001000000000 &
b1100001000000000 *
1'
#55000
1!
b1100111111000000 "
b1100111111000000 ;
1$
#60000
0$
0'
#65000
0!
1$
#70000
0$
#75000
1$
#80000
b1100101000000000 /
b10010 R
b100000000000 Q
b10010 8
b10010 O
b1000000000 3
b1000000000 P
b100000000000 N
b11100000000000 2
b11100000000000 >
b11100000000000 L
b1101100000000 B
1<
0$
b1100010100000000 %
b1100010100000000 )
1'
#85000
1!
b1100101000000000 "
b1100101000000000 ;
1$
#90000
0$
0'
#95000
0!
1$
#100000
0$
#105000
1$
#110000
b100111010100000 /
b10101000000 N
b101010000000 Q
b10011 R
0.
b10011 8
b10011 O
b1010100000 3
b1010100000 P
0M
b10000000000 4
b10000000000 F
b10100 1
b10100 J
b10100 K
b10000000000 5
b10000000000 ?
b10000000000 I
b101000000 7
b101000000 @
b101000000 H
b10 G
b10000000000 A
b10101000000 2
b10101000000 >
b10101000000 L
b101000000 B
b10011 D
0=
0<
0$
b100110000000000 &
b100110000000000 *
b100010100000000 %
b100010100000000 )
1'
#115000
1!
b100111010100000 "
b100111010100000 ;
1$
#120000
0$
0'
#125000
0!
1$
#130000
0$
#135000
1$
#140000
10
b111110000000000 /
b11111111111 N
b11110 R
b111111111110 Q
b11110 8
b11110 O
b1111111111 3
b1111111111 P
b0 A
b11111111111 2
b11111111111 >
b11111111111 L
b11111111111 B
b11111111111 6
b11111111111 E
b11111 1
b11111 J
b11111 K
b0 5
b0 ?
b0 I
b11111111111 7
b11111111111 @
b11111111111 H
b1011 G
b11110 C
0$
b111101111111111 %
b111101111111111 )
1'
#145000
1#
1!
b111110000000000 "
b111110000000000 ;
1$
#150000
0$
0'
#155000
0!
1$
#160000
0$
#165000
1$
#170000
b10100000000 N
b10100000000 2
b10100000000 >
b10100000000 L
b10100000000 B
b111110000000000 /
b10001 R
b101000000000 Q
10
b10001 8
b10001 O
b1010000000 3
b1010000000 P
b0 4
b0 F
b10100000000 6
b10100000000 E
b10010 1
b10010 J
b10010 K
b10100000000 7
b10100000000 @
b10100000000 H
b10001 G
1,
b0 D
b10001 C
0$
b0 &
b0 *
b100010100000000 %
b100010100000000 )
1'
#175000
1!
1$
#180000
0$
0'
#185000
0!
1$
#190000
0$
#195000
1$
#200000
b0 N
b0 2
b0 >
b0 L
b0 B
b0 /
b0 R
b101000000000 Q
00
b0 8
b0 O
b0 3
b0 P
1+
b0 6
b0 E
b1 1
b1 J
b1 K
b0 7
b0 @
b0 H
b0 G
1-
b0 C
0$
b0 %
b0 )
1'
#205000
0#
1!
b0 "
b0 ;
1$
#210000
0$
0'
#215000
0!
1$
